udacityproject_distributions/Binomialdistribution.py
udacityproject_distributions/Gaussiandistribution.py
udacityproject_distributions/Generaldistribution.py
udacityproject_distributions/__init__.py
udacityproject_distributions-0.6.dist-info/METADATA
udacityproject_distributions-0.6.dist-info/WHEEL
udacityproject_distributions-0.6.dist-info/top_level.txt
udacityproject_distributions-0.6.dist-info/RECORD
