Metadata-Version: 2.1
Name: udacityproject-distributions
Version: 0.6
Summary: Distributions
Home-page: UNKNOWN
Author: Kimosh7
Author-email: kimotho.wangari@aims-cameroon.org
License: UNKNOWN
Platform: UNKNOWN
